thunder_ml/__init__.py
thunder_ml/callbacks/__init__.py
thunder_ml/callbacks/conf_matrix.py
thunder_ml/callbacks/reg_plot.py
thunder_ml/modules/__init__.py
thunder_ml/modules/thunder_module.py
thunder_ml/routines/__init__.py
thunder_ml/routines/inference_mode.py
thunder_ml-0.1.1.dist-info/METADATA
thunder_ml-0.1.1.dist-info/WHEEL
thunder_ml-0.1.1.dist-info/RECORD
